hidman/__init__.py
hidman/core.py
hidman-1.0.dist-info/LICENSE
hidman-1.0.dist-info/METADATA
hidman-1.0.dist-info/WHEEL
hidman-1.0.dist-info/top_level.txt
hidman-1.0.dist-info/RECORD
