Metadata-Version: 2.1
Name: hidman
Version: 1.0
Summary: A Python based HID (Human Interface Device) events manager
Home-page: http://github.com/s4hri/hidman
Author: Davide De Tommaso
Author-email: davide.detommaso@iit.it
License: MIT
Platform: UNKNOWN
License-File: LICENSE
Requires-Dist: pytest (>=6.2.4)
Requires-Dist: evdev (>=1.4.0)
Requires-Dist: pyzmq (>=22.1.0)
